{
	"name": "ls_databricks_banking",
	"properties": {
		"annotations": [],
		"type": "AzureDatabricks",
		"typeProperties": {
			"domain": "https://adb-7405617027258960.0.azuredatabricks.net",
			"accessToken": {
				"type": "AzureKeyVaultSecret",
				"store": {
					"referenceName": "ls_keyvault_banking",
					"type": "LinkedServiceReference"
				},
				"secretName": "databricks-token",
				"secretVersion": "ad4e2e46a2164650a0bf6ec00dd9f4e3"
			},
			"existingClusterId": "0430-221045-x0d6v2l3"
		}
	},
	"type": "Microsoft.DataFactory/factories/linkedservices"
}